satsense/__init__.py
satsense/_version.py
satsense/bands.py
satsense/extract.py
satsense/generators.py
satsense/image.py
satsense/features/__init__.py
satsense/features/feature.py
satsense/features/hog.py
satsense/features/lacunarity.py
satsense/features/ndxi.py
satsense/features/pantex.py
satsense/features/sift.py
satsense/features/texton.py
satsense/performance/__init__.py
satsense/performance/jaccard_similarity.py
satsense/util/__init__.py
satsense/util/conversions.py
satsense/util/mask.py
satsense/util/shapefile.py
test/__init__.py
test/conftest.py
test/strategies.py
test/test_extract.py
test/test_generators.py
test/test_image.py
test/data/baseimage/section_2_sentinel_canny_edge.tif
test/data/baseimage/section_2_sentinel_gray_ubyte.tif
test/data/baseimage/section_2_sentinel_grayscale.tif
test/data/baseimage/section_2_sentinel_textons.tif
test/data/generate/baseimage.py
test/data/generate/feature_target.py
test/data/source/section_2_sentinel.tif
test/data/source/section_2_sentinel_l1c.tif
test/data/source/section_2_sentinel_rect.tif
test/data/source/section_2_sentinel_rect_wgs84.tif
test/data/target/hog.nc
test/data/target/lacunarity.nc
test/data/target/ndsi.tif
test/data/target/ndsi.tif.msk
test/data/target/ndvi.tif
test/data/target/ndvi.tif.msk
test/data/target/pantex.nc
test/data/target/rb_ndvi.tif
test/data/target/rb_ndvi.tif.msk
test/data/target/rg_ndvi.tif
test/data/target/rg_ndvi.tif.msk
test/data/target/sift.nc
test/data/target/texton.nc
test/features/gen_target.py
test/features/test_baseimage.py
test/features/test_features.py
satsense-0.9.dist-info/LICENSE
satsense-0.9.dist-info/METADATA
satsense-0.9.dist-info/WHEEL
satsense-0.9.dist-info/top_level.txt
satsense-0.9.dist-info/RECORD
