Metadata-Version: 2.1
Name: satsense
Version: 0.9
Summary: Library for multispectral remote imaging.
Home-page: https://github.com/DynaSlum/SateliteImaging
Author: Berend Weel, Elena Ranguelova, Bouwe Andela, Maximilian Filtenborg, Derk Barten, Yifat Dzigan, Ronald van Haren, Niels Drost
Author-email: b.weel@esiencecenter.nl
License: Apache Software License
Platform: any
Classifier: Programming Language :: Python
Classifier: Programming Language :: Python :: 3
Classifier: Programming Language :: Python :: 3.6
Classifier: Programming Language :: Python :: 3.7
Classifier: Development Status :: 4 - Beta
Classifier: Natural Language :: English
Classifier: Intended Audience :: Developers
Classifier: License :: OSI Approved :: Apache Software License
Classifier: Operating System :: OS Independent
Classifier: Topic :: Software Development :: Libraries :: Python Modules
Requires-Dist: affine
Requires-Dist: descartes
Requires-Dist: fiona
Requires-Dist: netCDF4
Requires-Dist: numpy
Requires-Dist: opencv-contrib-python-headless (<3.4.3)
Requires-Dist: rasterio
Requires-Dist: scikit-image (>=0.14.2)
Requires-Dist: scikit-learn
Requires-Dist: scipy
Requires-Dist: shapely
Provides-Extra: dev
Requires-Dist: hypothesis[numpy] ; extra == 'dev'
Requires-Dist: isort ; extra == 'dev'
Requires-Dist: pycodestyle ; extra == 'dev'
Requires-Dist: pyflakes ; extra == 'dev'
Requires-Dist: prospector[with_pyroma] ; extra == 'dev'
Requires-Dist: pytest ; extra == 'dev'
Requires-Dist: pytest-cov ; extra == 'dev'
Requires-Dist: pytest-env ; extra == 'dev'
Requires-Dist: pytest-flake8 ; extra == 'dev'
Requires-Dist: pytest-html ; extra == 'dev'
Requires-Dist: sphinx ; extra == 'dev'
Requires-Dist: sphinx-rtd-theme ; extra == 'dev'
Requires-Dist: yamllint ; extra == 'dev'
Requires-Dist: yapf ; extra == 'dev'
Provides-Extra: notebooks
Requires-Dist: jupyter ; extra == 'notebooks'
Requires-Dist: matplotlib ; extra == 'notebooks'
Requires-Dist: nblint ; extra == 'notebooks'
